MANIFEST.in
README.rst
setup.py
miur_daad_balancing/__init__.py
miur_daad_balancing/__version__.py
miur_daad_balancing/balanced.json
miur_daad_balancing/balanced.py
miur_daad_balancing/full_balanced.json
miur_daad_balancing/full_balanced.py
miur_daad_balancing/get_callback.py
miur_daad_balancing/umbalanced.py
miur_daad_balancing.egg-info/PKG-INFO
miur_daad_balancing.egg-info/SOURCES.txt
miur_daad_balancing.egg-info/dependency_links.txt
miur_daad_balancing.egg-info/requires.txt
miur_daad_balancing.egg-info/top_level.txt
miur_daad_balancing/originals/__init__.py
miur_daad_balancing/originals/sampling_class_portion.py
miur_daad_balancing/originals/truncate_sample_size.py
miur_daad_balancing/utils/__init__.py
miur_daad_balancing/utils/current_path.py
miur_daad_balancing/utils/get_classes.py
miur_daad_balancing/utils/load_balanced.py
miur_daad_balancing/utils/load_data.py
miur_daad_balancing/utils/load_full_balanced.py