Metadata-Version: 2.1
Name: miur-daad-balancing
Version: 1.0.0
Summary: Testing dataset balancing techniques from previous works.
Home-page: https://github.com/LucaCappelletti94/miur_daad_balancing
Author: Luca Cappelletti
Author-email: cappelletti.luca94@gmail.com
License: MIT
Platform: UNKNOWN
Classifier: Development Status :: 3 - Alpha
Classifier: License :: OSI Approved :: MIT License
Classifier: Programming Language :: Python :: 3
Provides-Extra: test
